iiitb_sdMoore.v
module morfsmolp(din, reset, clk, y);
input din;
input clk;
input reset;
output reg y;
reg [2:0] cst, nst;
parameter S0 = 3'b000,
          S1 = 3'b001,
          S2 = 3'b010,
          S3 = 3'b100,
          S4 = 3'b101;
always @(cst or din)
 begin
 case (cst)
   S0: if (din == 1'b1)
          begin
         nst = S1;
          y=1'b0;
          end
      else nst = cst;
   S1: if (din == 1'b0)
          begin
        nst = S2;
          y=1'b0;
          end
       else
          begin
          nst = cst;
          y=1'b0;
          end
   S2: if (din == 1'b1)
          begin
         nst = S3;
          y=1'b0;
          end    
        else
          begin
          nst = S0;
          y=1'b0;
          end
   S3: if (din == 1'b0)
          begin
         nst = S4;
          y=1'b0;
          end
       else
          begin
          nst = S1;
          y=1'b0;
          end
   S4: if (din == 1'b0)
          begin
         nst = S1;
          y=1'b1;
          end
          else
          begin
          nst = S3;
          y=1'b1;
          end
   default: nst = S0;
  endcase
end
always@(posedge clk)
begin
          if (reset)
            cst <= S0;
          else
            cst <= nst;
end
endmodule

iiitb_sdMoore_tb.v
module morfsmolp_tb;
reg din,clk,reset;
wire y;
morfsmolp m1(din, reset, clk, y);
initial
begin

$dumpfile("test2.vcd");
$dumpvars(0,morfsmolp_tb);
reset=0       ;clk=0;din=0;
$monitor($time, , ,"c=%b",clk,,"y=%b",y,,"r=%b",reset,,"d=%b",din);
#10 din=1;
#10 din=1;
#10 din=1;
#10 din=0;
#10 din=1;
#10 din=0;
#10 din=1;
#10 din=0;
#10 din=1;
//#5 reset=1;
//#5 reset=0;
end
always
#5 clk=~clk;
initial
#100 $finish ;
endmodule

test2.vcd
$date
	Fri Aug  5 14:37:59 2022
$end
$version
	Icarus Verilog
$end
$timescale
	1s
$end
$scope module morfsmolp_tb $end
$var wire 1 ! y $end
$var reg 1 " clk $end
$var reg 1 # din $end
$var reg 1 $ reset $end
$scope module m1 $end
$var wire 1 " clk $end
$var wire 1 # din $end
$var wire 1 $ reset $end
$var reg 3 % cst [2:0] $end
$var reg 3 & nst [2:0] $end
$var reg 1 ! y $end
$upscope $end
$upscope $end
$enddefinitions $end
#0
$dumpvars
b0 &
bx %
0$
0#
0"
x!
$end
#5
b0 %
1"
#10
0!
b1 &
0"
1#
#15
b1 %
1"
#20
0"
#25
1"
#30
0"
#35
1"
#40
b10 &
0"
0#
#45
b0 &
b10 %
1"
#50
b100 &
0"
1#
#55
b1 &
b100 %
1"
#60
b101 &
0"
0#
#65
1!
b1 &
b101 %
1"
#70
b100 &
0"
1#
#75
0!
b1 &
b100 %
1"
#80
b101 &
0"
0#
#85
1!
b1 &
b101 %
1"
#90
b100 &
0"
1#
#95
0!
b1 &
b100 %
1"
